unihasher/NMF_Hash.py
unihasher/__init__.py
unihasher/hash.py
unihasher/unihasher.py
unihasher-0.1.5.dist-info/LICENSE
unihasher-0.1.5.dist-info/METADATA
unihasher-0.1.5.dist-info/WHEEL
unihasher-0.1.5.dist-info/top_level.txt
unihasher-0.1.5.dist-info/RECORD
