Metadata-Version: 2.1
Name: unihasher
Version: 0.1.5
Summary: Compare image hashes using a unified library
Home-page: https://github.com/Cp-Youfy/unihasher
Author: Akshara Mantha, Peng Ruijia, Tan Siying
Author-email: cpyoufy@gmail.com
License: MIT
Classifier: Intended Audience :: Developers
Classifier: License :: OSI Approved :: MIT License
Classifier: Programming Language :: Python
Classifier: Programming Language :: Python :: 3
Classifier: Programming Language :: Python :: 3.6
Classifier: Programming Language :: Python :: 3.7
Classifier: Programming Language :: Python :: 3.8
Classifier: Programming Language :: Python :: 3.9
Classifier: Operating System :: OS Independent
License-File: LICENSE
Requires-Dist: imagehash
Requires-Dist: pillow
Requires-Dist: opencv-python
Requires-Dist: setuptools
